cdk_ec2_spot_simple/__init__.py
cdk_ec2_spot_simple/py.typed
cdk_ec2_spot_simple/_jsii/__init__.py
cdk_ec2_spot_simple/_jsii/cdk-ec2-spot-simple@2.2.0.jsii.tgz
cdk_ec2_spot_simple-2.2.0.dist-info/LICENSE
cdk_ec2_spot_simple-2.2.0.dist-info/METADATA
cdk_ec2_spot_simple-2.2.0.dist-info/WHEEL
cdk_ec2_spot_simple-2.2.0.dist-info/top_level.txt
cdk_ec2_spot_simple-2.2.0.dist-info/RECORD
